sshauthproxy.py
sshauthproxy-0.1.dist-info/LICENSE
sshauthproxy-0.1.dist-info/METADATA
sshauthproxy-0.1.dist-info/WHEEL
sshauthproxy-0.1.dist-info/entry_points.txt
sshauthproxy-0.1.dist-info/top_level.txt
sshauthproxy-0.1.dist-info/RECORD
