Metadata-Version: 2.1
Name: sshauthproxy
Version: 0.1
Summary: SSH AuthorizedKeysCommand proxy: publish your SSH authorized_keys from an existing AuthorizedKeysCommand
Home-page: https://github.com/quantum5/sshauthproxy
Author: quantum
Author-email: quantum2048@gmail.com
License: AGPLv3
Keywords: ssh public-key proxy authorized_keys
Platform: UNKNOWN
Classifier: Development Status :: 3 - Alpha
Classifier: Environment :: No Input/Output (Daemon)
Classifier: Intended Audience :: System Administrators
Classifier: License :: OSI Approved :: GNU Affero General Public License v3
Classifier: Operating System :: POSIX
Classifier: Programming Language :: Python
Classifier: Programming Language :: Python :: 2
Classifier: Programming Language :: Python :: 2.7
Classifier: Programming Language :: Python :: 3
Classifier: Programming Language :: Python :: 3.4
Classifier: Programming Language :: Python :: 3.5
Classifier: Programming Language :: Python :: 3.6
Classifier: Programming Language :: Python :: 3.7
Classifier: Topic :: System :: Systems Administration :: Authentication/Directory
Classifier: Topic :: Utilities
Requires-Dist: tornado
